linkedincv/__init__.py
linkedincv/cli/__init__.py
linkedincv/cli/command.py
linkedincv/cli/core.py
linkedincv/config.py
linkedincv/constants.py
linkedincv/cv/__init__.py
linkedincv/cv/models/__init__.py
linkedincv/cv/models/core.py
linkedincv/cv/models/experience.py
linkedincv/cv/models/meta.py
linkedincv/cv/models/qualification.py
linkedincv/template/main.tex
linkedin_cv-0.1.1.dist-info/entry_points.txt
linkedin_cv-0.1.1.dist-info/LICENSE
linkedin_cv-0.1.1.dist-info/WHEEL
linkedin_cv-0.1.1.dist-info/METADATA
linkedin_cv-0.1.1.dist-info/RECORD
